LAS/__init__.py
LAS/converter.py
las_converter-0.4.0.data/scripts/converter
test/__init__.py
test/expected.py
test/test_converter.py
las_converter-0.4.0.dist-info/LICENSE
las_converter-0.4.0.dist-info/METADATA
las_converter-0.4.0.dist-info/WHEEL
las_converter-0.4.0.dist-info/top_level.txt
las_converter-0.4.0.dist-info/RECORD
