Metadata-Version: 2.1
Name: las-converter
Version: 0.4.0
Summary: Converter LAS file to python dictionary and json file
Home-page: https://github.com/josestnggng/Las-converter
Author: Jose Sitanggang, Asido Sigalingging
Author-email: jose.stnggng@gmail.com,asido.saputra@gmail.com
License: UNKNOWN
Platform: UNKNOWN
Classifier: Programming Language :: Python :: 3
Classifier: License :: OSI Approved :: MIT License
Classifier: Operating System :: OS Independent
